vizexpln/UI.py
vizexpln/__init__.py
vizexpln/generator.py
vizexpln/messages.py
vizexpln/plotter.py
vizexpln/prompts.py
vizexpln/report.py
vizexpln-0.1.0.dist-info/LICENSE
vizexpln-0.1.0.dist-info/METADATA
vizexpln-0.1.0.dist-info/WHEEL
vizexpln-0.1.0.dist-info/RECORD
