Metadata-Version: 2.1
Name: vizexpln
Version: 0.1.0
Summary: Seamlessly combine the power of Jupyter Notebooks and AI to visualize, and interpret your data. A low-code tool for data visualization and interpretation
Author: Nishanth
Author-email: nishanthkc009@gmail.com
Requires-Python: >=3.12,<4.0
Classifier: Programming Language :: Python :: 3
Classifier: Programming Language :: Python :: 3.12
Classifier: Programming Language :: Python :: 3.13
Requires-Dist: google-generativeai (>=0.8.3,<0.9.0)
Requires-Dist: ipywidgets (>=8.1.5,<9.0.0)
Requires-Dist: langchain (>=0.3.11,<0.4.0)
Requires-Dist: langchain-community (>=0.3.11,<0.4.0)
Requires-Dist: langchain-google-genai (>=2.0.7,<3.0.0)
Requires-Dist: pandas (>=2.2.3,<3.0.0)
Requires-Dist: pillow (>=11.0.0,<12.0.0)
Requires-Dist: python-dotenv (>=1.0.1,<2.0.0)
Requires-Dist: scikit-learn (>=1.5.2,<2.0.0)
Requires-Dist: seaborn (>=0.13.2,<0.14.0)
